{
  "version": "7",
  "dialect": "mysql",
  "entries": [
    {
      "idx": 0,
      "version": "5",
      "when": 1771856127503,
      "tag": "0000_married_sue_storm",
      "breakpoints": true
    },
    {
      "idx": 1,
      "version": "5",
      "when": 1771856429388,
      "tag": "0001_short_logan",
      "breakpoints": true
    },
    {
      "idx": 2,
      "version": "5",
      "when": 1771872783084,
      "tag": "0002_easy_typhoid_mary",
      "breakpoints": true
    },
    {
      "idx": 3,
      "version": "5",
      "when": 1772303991766,
      "tag": "0003_dazzling_elektra",
      "breakpoints": true
    },
    {
      "idx": 4,
      "version": "5",
      "when": 1773595696829,
      "tag": "0004_happy_white_queen",
      "breakpoints": true
    },
    {
      "idx": 5,
      "version": "5",
      "when": 1773693733189,
      "tag": "0005_glossy_obadiah_stane",
      "breakpoints": true
    }
  ]
}